shellp/__init__.py
shellp/__main__.py
shellp/builtin_commands.py
shellp/cmd_funcs.py
shellp/nothing.py
shellp/old_read_cmd.py
shellp/old_run.py
shellp/options.py
shellp/parse_bash_aliases.py
shellp/parse_prompt.py
shellp/run.py
shellp/run_pipes.py
shellp/split_cmd.py
shellp/utils.py
shellp-0.2.1.dist-info/METADATA
shellp-0.2.1.dist-info/RECORD
shellp-0.2.1.dist-info/WHEEL
shellp-0.2.1.dist-info/entry_points.txt
shellp-0.2.1.dist-info/top_level.txt
