Metadata-Version: 2.1
Name: shellp
Version: 0.2.1
Summary: An advanced and easy to configure shell
Home-page: https://github.com/dullbananas/shellp
Author: Dull Bananas
Author-email: dull.bananas0@gmail.com
License: GPLv2
Platform: UNKNOWN
Classifier: Development Status :: 3 - Alpha
Classifier: Environment :: Console
Classifier: License :: OSI Approved :: GNU General Public License v2 (GPLv2)
Classifier: Natural Language :: English
Classifier: Operating System :: Unix
Classifier: Programming Language :: Python :: 3 :: Only
Classifier: Topic :: System :: Shells
Requires-Python: >=3.6
Requires-Dist: beautiful-ansi
Requires-Dist: prompt-toolkit (>=2)
Requires-Dist: pygit2
Requires-Dist: pygments (>=0.6)
Requires-Dist: timeoutcontext
